jsii_library_template/__init__.py
jsii_library_template/py.typed
jsii_library_template/_jsii/__init__.py
jsii_library_template/_jsii/jsii-library-template@1.1.0.jsii.tgz
jsii_library_template-1.1.0.dist-info/METADATA
jsii_library_template-1.1.0.dist-info/WHEEL
jsii_library_template-1.1.0.dist-info/top_level.txt
jsii_library_template-1.1.0.dist-info/RECORD
