Metadata-Version: 2.1
Name: jsii-library-template
Version: 1.1.0
Summary: Template for jsii libraries
Home-page: https://github.com/eladb/jsii-library-template.git
Author: Elad Ben-Israel<benisrae@amazon.com>
License: Apache-2.0
Project-URL: Source, https://github.com/eladb/jsii-library-template.git
Platform: UNKNOWN
Classifier: Intended Audience :: Developers
Classifier: Operating System :: OS Independent
Classifier: Programming Language :: JavaScript
Classifier: Programming Language :: Python :: 3 :: Only
Classifier: Programming Language :: Python :: 3.6
Classifier: Programming Language :: Python :: 3.7
Classifier: Programming Language :: Python :: 3.8
Classifier: Typing :: Typed
Classifier: Development Status :: 4 - Beta
Classifier: License :: OSI Approved
Requires-Python: >=3.6
Requires-Dist: jsii (<2.0.0,>=1.5.0)
Requires-Dist: publication (>=0.0.3)
